process_image.py
brain_paint-0.0.6.dist-info/LICENSE
brain_paint-0.0.6.dist-info/METADATA
brain_paint-0.0.6.dist-info/WHEEL
brain_paint-0.0.6.dist-info/entry_points.txt
brain_paint-0.0.6.dist-info/top_level.txt
brain_paint-0.0.6.dist-info/RECORD
