Metadata-Version: 2.1
Name: brain-paint
Version: 0.0.6
Summary: Script for visualizing ICA/ROI brain parcellation
Author-email: paavali.popov@gmail.com, s.m.plis@gmail.com
Project-URL: Homepage, https://github.com/neuroneural/brain-paint
Project-URL: Bug Tracker, https://github.com/neuroneural/brain-paint/issues
Classifier: Programming Language :: Python :: 3
Classifier: License :: OSI Approved :: MIT License
Classifier: Operating System :: OS Independent
Requires-Python: >=3.7
License-File: LICENSE
Requires-Dist: numpy
Requires-Dist: nipy
Requires-Dist: matplotlib
